odoo/addons/companyweb_payment_info/README.rst
odoo/addons/companyweb_payment_info/__init__.py
odoo/addons/companyweb_payment_info/__manifest__.py
odoo/addons/companyweb_payment_info/i18n/companyweb_payment_info.pot
odoo/addons/companyweb_payment_info/i18n/es.po
odoo/addons/companyweb_payment_info/i18n/fr.po
odoo/addons/companyweb_payment_info/i18n/nl.po
odoo/addons/companyweb_payment_info/readme/CONTRIBUTORS.md
odoo/addons/companyweb_payment_info/readme/CREDITS.md
odoo/addons/companyweb_payment_info/readme/DESCRIPTION.md
odoo/addons/companyweb_payment_info/readme/INSTALL.md
odoo/addons/companyweb_payment_info/readme/USAGE.md
odoo/addons/companyweb_payment_info/security/ir.model.access.csv
odoo/addons/companyweb_payment_info/security/security.xml
odoo/addons/companyweb_payment_info/static/description/doc_companyweb_data.png
odoo/addons/companyweb_payment_info/static/description/icon.png
odoo/addons/companyweb_payment_info/static/description/index.html
odoo/addons/companyweb_payment_info/static/img/logo-en.png
odoo/addons/companyweb_payment_info/static/img/logo-en.resized.png
odoo/addons/companyweb_payment_info/tests/__init__.py
odoo/addons/companyweb_payment_info/tests/test_cweb_upload.py
odoo/addons/companyweb_payment_info/tests/cassettes/TestUpload.test_upload_payment.yaml
odoo/addons/companyweb_payment_info/wizards/__init__.py
odoo/addons/companyweb_payment_info/wizards/credential_wizard_payment.py
odoo/addons/companyweb_payment_info/wizards/payment_info_wizard.py
odoo/addons/companyweb_payment_info/wizards/payment_info_wizard.xml
odoo_addon_companyweb_payment_info-18.0.1.0.1.3.dist-info/METADATA
odoo_addon_companyweb_payment_info-18.0.1.0.1.3.dist-info/WHEEL
odoo_addon_companyweb_payment_info-18.0.1.0.1.3.dist-info/top_level.txt
odoo_addon_companyweb_payment_info-18.0.1.0.1.3.dist-info/RECORD
