Metadata-Version: 2.1
Name: odoo-addon-companyweb_payment_info
Version: 18.0.1.0.1.3
Requires-Python: >=3.10
Requires-Dist: odoo-addon-companyweb_base==18.0.*
Requires-Dist: odoo==18.0.*
Requires-Dist: zeep
Summary: Send your customer payment information to Companyweb
Home-page: https://github.com/OCA/l10n-belgium
License: AGPL-3
Author: ACSONE SA/NV,Odoo Community Association (OCA)
Author-email: support@odoo-community.org
Classifier: Programming Language :: Python
Classifier: Framework :: Odoo
Classifier: Framework :: Odoo :: 18.0
Classifier: License :: OSI Approved :: GNU Affero General Public License v3
Classifier: Development Status :: 5 - Production/Stable
